oarepo_model_builder_workflows/__init__.py
oarepo_model_builder_workflows/builders/__init__.py
oarepo_model_builder_workflows/builders/setup_cfg.py
oarepo_model_builder_workflows/builders/workflow_sample_data.py
oarepo_model_builder_workflows/datatypes/__init__.py
oarepo_model_builder_workflows/datatypes/components/__init__.py
oarepo_model_builder_workflows/datatypes/components/workflow.py
oarepo_model_builder_workflows-1.0.7.dist-info/METADATA
oarepo_model_builder_workflows-1.0.7.dist-info/WHEEL
oarepo_model_builder_workflows-1.0.7.dist-info/entry_points.txt
oarepo_model_builder_workflows-1.0.7.dist-info/top_level.txt
oarepo_model_builder_workflows-1.0.7.dist-info/RECORD
