Metadata-Version: 2.1
Name: oarepo-model-builder-workflows
Version: 1.0.7
Requires-Dist: oarepo-model-builder>=4.0.0
Requires-Dist: oarepo-model-builder-drafts>=4.0.0
Provides-Extra: tests
Requires-Dist: oarepo-model-builder-tests>=3.1.0; extra == "tests"
Requires-Dist: black; extra == "tests"
Requires-Dist: isort; extra == "tests"
Requires-Dist: autoflake; extra == "tests"
